pipflow/__init__.py
pipflow/__main__.py
Pipflow-0.0.6.dist-info/LICENSE
Pipflow-0.0.6.dist-info/METADATA
Pipflow-0.0.6.dist-info/WHEEL
Pipflow-0.0.6.dist-info/entry_points.txt
Pipflow-0.0.6.dist-info/top_level.txt
Pipflow-0.0.6.dist-info/RECORD
