Metadata-Version: 2.1
Name: Pipflow
Version: 0.0.6
Summary: Python Distribution Utilities
Home-page: https://github.com/iMerica/pipflow
Author: Michael Martinez
Author-email: imichael@pm.me
License: UNKNOWN
Keywords: Package Managers
Platform: UNKNOWN
Classifier: Development Status :: 3 - Alpha
Classifier: Intended Audience :: Developers
Classifier: Topic :: Software Development :: Build Tools
Classifier: License :: OSI Approved :: MIT License
Classifier: Programming Language :: Python :: 3.5
Classifier: Programming Language :: Python :: 3.6
Classifier: Programming Language :: Python :: 3.7
Classifier: Programming Language :: Python :: 3.8
Requires-Python: >=3.5
Requires-Dist: cleo
Requires-Dist: requests
